aerium_grpc/__init__.py
aerium_grpc/__init__.pyi
aerium_grpc/blockchain_pb2.py
aerium_grpc/blockchain_pb2.pyi
aerium_grpc/blockchain_pb2_grpc.py
aerium_grpc/network_pb2.py
aerium_grpc/network_pb2.pyi
aerium_grpc/network_pb2_grpc.py
aerium_grpc/transaction_pb2.py
aerium_grpc/transaction_pb2.pyi
aerium_grpc/transaction_pb2_grpc.py
aerium_grpc/utils_pb2.py
aerium_grpc/utils_pb2.pyi
aerium_grpc/utils_pb2_grpc.py
aerium_grpc/wallet_pb2.py
aerium_grpc/wallet_pb2.pyi
aerium_grpc/wallet_pb2_grpc.py
aerium_grpc-0.2.0.dist-info/licenses/LICENSE
aerium_grpc-0.2.0.dist-info/METADATA
aerium_grpc-0.2.0.dist-info/WHEEL
aerium_grpc-0.2.0.dist-info/top_level.txt
aerium_grpc-0.2.0.dist-info/RECORD
